dayan_sync/__init__.py
dayan_sync/constants.py
dayan_sync/db_config.ini
dayan_sync/download.py
dayan_sync/exception.py
dayan_sync/manage.py
dayan_sync/transfer.py
dayan_sync/upload.py
dayan_sync/utils.py
dayan_sync/tests/__init__.py
dayan_sync/tests/conftest.py
dayan_sync/tests/test_manage.py
dayan_sync/tests/test_transfer.py
dayan_sync/tests/test_upload.py
dayan_sync/tests/test_utils.py
dayan_sync/transmission/db.ini
dayan_sync/transmission/transports.json
dayan_sync/transmission/usage.txt
dayan_sync/transmission/linux/rayvision_transmitter
dayan_sync/transmission/linux/aspera/ascmd
dayan_sync/transmission/linux/aspera/ascp
dayan_sync/transmission/linux/aspera/aspera-license
dayan_sync/transmission/linux/aspera/aspshell
dayan_sync/transmission/linux/aspera/astokengen
dayan_sync/transmission/linux/raysync/killproxy.sh
dayan_sync/transmission/linux/raysync/raysyncproxy
dayan_sync/transmission/windows/RaySync-Multi-Proxy-Client.dll
dayan_sync/transmission/windows/RaySync.dll
dayan_sync/transmission/windows/aes_ecb.dll
dayan_sync/transmission/windows/aspera_engine.dll
dayan_sync/transmission/windows/cmarkup.dll
dayan_sync/transmission/windows/hiredis.dll
dayan_sync/transmission/windows/json.dll
dayan_sync/transmission/windows/libAuthentication.dll
dayan_sync/transmission/windows/libjson.dll
dayan_sync/transmission/windows/libsqlite.dll
dayan_sync/transmission/windows/license.log
dayan_sync/transmission/windows/raysync_engine.dll
dayan_sync/transmission/windows/rayvision_transmitter.exe
dayan_sync/transmission/windows/stupid_base.dll
dayan_sync/transmission/windows/stupid_net.dll
dayan_sync/transmission/windows/transfer_pass.dll
dayan_sync/transmission/windows/xxhash.dll
dayan_sync/transmission/windows/aspera/ascp.exe
dayan_sync/transmission/windows/aspera/fasp3.dll
dayan_sync/transmission/windows/aspera/faspstream.exe
dayan_sync/transmission/windows/aspera/libeay32.dll
dayan_sync/transmission/windows/aspera/msvcr100.dll
dayan_sync-1.0.dist-info/LICENSE
dayan_sync-1.0.dist-info/METADATA
dayan_sync-1.0.dist-info/WHEEL
dayan_sync-1.0.dist-info/top_level.txt
dayan_sync-1.0.dist-info/RECORD
