Metadata-Version: 2.1
Name: dayan-sync
Version: 1.0
Summary: Upload configuration file and asset file, download result file.
Home-page: https://github.com/internal/dayan_sync
Author: Shenzhen Rayvision Technology Co., Ltd
Author-email: developer@rayvision.com
License: UNKNOWN
Platform: UNKNOWN
Classifier: Programming Language :: Python
Classifier: Programming Language :: Python :: 3
Requires-Dist: rayvision-log (>=0.3.3)
Requires-Dist: requests (==2.23.0)
Requires-Dist: configparser (==4.0.2)
Requires-Dist: tenacity (==6.0.0)
Requires-Dist: dayan-api (>=1.6)
